{
  "dependencies": {
    "secrets1": {
      "type": "secrets"
    },
    "appInsights1": {
      "type": "appInsights",
      "connectionId": "APPINSIGHTS_CONNECTIONSTRING"
    },
    "mssql1": {
      "type": "mssql",
      "connectionId": "ConnectionStrings:DefaultConnection"
    },
    "mssql2": {
      "type": "mssql",
      "connectionId": "ConnectionStrings:CatalogDbConnection"
    },
    "cosmosdb1": {
      "type": "cosmosdb",
      "connectionId": "ConnectionStrings:CosmosDb"
    }
  }
}